slim/__init__.py
slim/exception.py
slim/retcode.py
slim/base/__init__.py
slim/base/app.py
slim/base/const.py
slim/base/helper.py
slim/base/log.py
slim/base/permission.py
slim/base/route.py
slim/base/session.py
slim/base/sqlfuncs.py
slim/base/sqlquery.py
slim/base/staticfile.py
slim/base/staticfiles.py
slim/base/user.py
slim/base/view.py
slim/base/web.py
slim/base/ws.py
slim/base/_view/__init__.py
slim/base/_view/abstract_sql_view.py
slim/base/_view/base_view.py
slim/base/_view/err_catch_context.py
slim/base/_view/request_view.py
slim/base/_view/validate.py
slim/base/_view/view_options.py
slim/base/types/__init__.py
slim/base/types/asgi.py
slim/base/types/beacon.py
slim/base/types/doc.py
slim/base/types/func_meta.py
slim/base/types/inner_interface_name.py
slim/base/types/route_meta_info.py
slim/base/types/route_view_info.py
slim/base/types/temp_storage.py
slim/ext/__init__.py
slim/ext/decorator.py
slim/ext/openapi/__init__.py
slim/ext/openapi/main.py
slim/ext/openapi/serve.py
slim/support/__init__.py
slim/support/asyncpg/__init__.py
slim/support/asyncpg/query.py
slim/support/asyncpg/view.py
slim/support/peewee/__init__.py
slim/support/peewee/data_record.py
slim/support/peewee/sqlfuncs.py
slim/support/peewee/validate.py
slim/support/peewee/view.py
slim/tools/__init__.py
slim/tools/request.py
slim/tools/test.py
slim/utils/__init__.py
slim/utils/async_run.py
slim/utils/autoload.py
slim/utils/binhex.py
slim/utils/cls_init.py
slim/utils/cls_property.py
slim/utils/cookies.py
slim/utils/count_dict.py
slim/utils/customid.py
slim/utils/exceptions.py
slim/utils/jsdict.py
slim/utils/json_ex.py
slim/utils/myobjectid.py
slim/utils/pagination.py
slim/utils/proxy.py
slim/utils/ref.py
slim/utils/repath.py
slim/utils/schematics_ext.py
slim/utils/state_obj.py
slim/utils/types.py
slim/utils/umsgpack.py
slim/utils/win_ioloop_ctrlc_patch.py
slim_cli/__init__.py
slim_cli/main.py
slim_cli/template/.gitignore
slim_cli/template/app.py
slim_cli/template/config.py
slim_cli/template/main.py
slim-0.6.2.dist-info/LICENSE
slim-0.6.2.dist-info/METADATA
slim-0.6.2.dist-info/WHEEL
slim-0.6.2.dist-info/entry_points.txt
slim-0.6.2.dist-info/top_level.txt
slim-0.6.2.dist-info/RECORD
