Metadata-Version: 2.1
Name: slim
Version: 0.6.2
Summary: A Web framework provides instant restful api for your database.
Home-page: https://github.com/fy0/slim
Author: fy
Author-email: fy0748@gmail.com
License: zlib
Keywords: slim web framework model asgi asyncpg peewee
Platform: any
Classifier: Development Status :: 4 - Beta
Classifier: Intended Audience :: Developers
Classifier: Topic :: Internet :: WWW/HTTP
Classifier: Topic :: Internet :: WWW/HTTP :: HTTP Servers
Classifier: Topic :: Software Development :: Libraries :: Python Modules
Classifier: Framework :: AsyncIO
Classifier: License :: OSI Approved :: zlib/libpng License
Classifier: Operating System :: OS Independent
Classifier: Programming Language :: Python
Classifier: Programming Language :: Python :: 3 :: Only
Classifier: Programming Language :: Python :: 3.6
Classifier: Programming Language :: Python :: 3.7
Classifier: Programming Language :: Python :: 3.8
Requires-Python: >=3.6.9
Requires-Dist: schematics (<2.2.0,>=2.1.0)
Requires-Dist: typing-extensions (>=3.6.5)
Requires-Dist: dataclasses
Requires-Dist: multidict (<5.0,>=4.5)
Requires-Dist: yarl (<1.5,>=1.0)
Requires-Dist: uvicorn (<0.12.0,>0.11.0)
Requires-Dist: click (<8.0,>=7.0)
Requires-Dist: aiofiles (<0.6,>=0.4.0)
Requires-Dist: python-multipart (==0.0.5)
Requires-Dist: msgpack (<2.0,>=0.5.6)
Provides-Extra: asyncpg
Requires-Dist: asyncpg ; extra == 'asyncpg'
Provides-Extra: dev
Requires-Dist: pytest ; extra == 'dev'
Requires-Dist: pytest-cov ; extra == 'dev'
Requires-Dist: pytest-asyncio ; extra == 'dev'
Requires-Dist: peewee ; extra == 'dev'
Requires-Dist: asyncpg ; extra == 'dev'
Requires-Dist: msgpack ; extra == 'dev'
Requires-Dist: psycopg2-binary ; extra == 'dev'
Provides-Extra: full
Requires-Dist: peewee ; extra == 'full'
Requires-Dist: asyncpg ; extra == 'full'
Requires-Dist: msgpack ; extra == 'full'
Requires-Dist: psycopg2-binary ; extra == 'full'
Provides-Extra: peewee
Requires-Dist: peewee ; extra == 'peewee'
Requires-Dist: psycopg2-binary ; extra == 'peewee'
